DogCity/.env
DogCity/DOGCITY.py
DogCity/Entry.py
DogCity/SupportFunctions.py
DogCity/__init__.py
dogcity-1.20.dist-info/METADATA
dogcity-1.20.dist-info/WHEEL
dogcity-1.20.dist-info/entry_points.txt
dogcity-1.20.dist-info/RECORD
